{
  "matchId": "2038871",
  "homeTeam": {
    "teamId": "2601744",
    "teamName": "2601744",
    "goals": 0,
    "attempts": 9,
    "attemptsOnTarget": 4,
    "attemptsOffTarget": 5,
    "attemptsBlocked": 0,
    "attemptsSaved": 0,
    "shotAccuracy": 44,
    "foulsCommitted": 5,
    "foulsSuffered": 7,
    "yellowCards": 2,
    "redCards": 0,
    "corners": 3,
    "woodworkHits": 0,
    "assists": 0,
    "freeKicksOnGoal": 0,
    "ownGoals": 0,
    "playedTimeMinutes": 89
  },
  "awayTeam": {
    "teamId": "2612898",
    "teamName": "2612898",
    "goals": 4,
    "attempts": 34,
    "attemptsOnTarget": 14,
    "attemptsOffTarget": 20,
    "attemptsBlocked": 0,
    "attemptsSaved": 0,
    "shotAccuracy": 41,
    "foulsCommitted": 7,
    "foulsSuffered": 5,
    "yellowCards": 2,
    "redCards": 0,
    "corners": 10,
    "woodworkHits": 3,
    "assists": 0,
    "freeKicksOnGoal": 0,
    "ownGoals": 1,
    "playedTimeMinutes": 89
  }
}