{
  "matchId": "2039631",
  "homeTeam": {
    "teamId": "2611095",
    "teamName": "2611095",
    "goals": 3,
    "attempts": 20,
    "attemptsOnTarget": 11,
    "attemptsOffTarget": 9,
    "attemptsBlocked": 0,
    "attemptsSaved": 0,
    "shotAccuracy": 55,
    "foulsCommitted": 8,
    "foulsSuffered": 8,
    "yellowCards": 2,
    "redCards": 0,
    "corners": 3,
    "woodworkHits": 1,
    "assists": 0,
    "freeKicksOnGoal": 0,
    "ownGoals": 0,
    "playedTimeMinutes": 90
  },
  "awayTeam": {
    "teamId": "2612932",
    "teamName": "2612932",
    "goals": 4,
    "attempts": 27,
    "attemptsOnTarget": 13,
    "attemptsOffTarget": 14,
    "attemptsBlocked": 0,
    "attemptsSaved": 0,
    "shotAccuracy": 48,
    "foulsCommitted": 8,
    "foulsSuffered": 8,
    "yellowCards": 4,
    "redCards": 0,
    "corners": 12,
    "woodworkHits": 1,
    "assists": 0,
    "freeKicksOnGoal": 0,
    "ownGoals": 0,
    "playedTimeMinutes": 90
  }
}